setup.py
pytomo3d/__init__.py
pytomo3d.egg-info/PKG-INFO
pytomo3d.egg-info/SOURCES.txt
pytomo3d.egg-info/dependency_links.txt
pytomo3d.egg-info/not-zip-safe
pytomo3d.egg-info/pbr.json
pytomo3d.egg-info/requires.txt
pytomo3d.egg-info/top_level.txt
pytomo3d/adjoint/__init__.py
pytomo3d/adjoint/adjsrc.py
pytomo3d/adjoint/dd_adjsrc.py
pytomo3d/adjoint/plot_util.py
pytomo3d/signal/__init__.py
pytomo3d/signal/process.py
pytomo3d/signal/rotate.py
pytomo3d/window/__init__.py
pytomo3d/window/window.py
pytomo3d/window/write_window.py