Metadata-Version: 1.1
Name: pytomo3d
Version: 0.1.0
Summary: Python toolkits for seismic tomograpy
Home-page: https://github.com/wjlei1990/pytomo3d
Author: Wenjie Lei
Author-email: lei@princeton.edu
License: GNU General Public License, Version 3 (GPLv3)
Keywords: seismology,tomography,adjoint,signal,inversion,window
Platform: UNKNOWN
Classifier: Development Status :: 4 - Beta
Classifier: Intended Audience :: Developers
Classifier: Intended Audience :: Science/Research
Classifier: Operating System :: Unix
Classifier: Operating System :: POSIX
Classifier: Operating System :: Microsoft :: Windows
Classifier: Programming Language :: Python
Classifier: Programming Language :: Python :: 2.7
Classifier: Programming Language :: Python :: Implementation :: CPython
Classifier: Topic :: Scientific/Engineering
Classifier: Topic :: Scientific/Engineering :: Physics
Classifier: License :: OSI Approved :: GNU General Public License v3 (GPLv3)
